competitive_verifier/__init__.py
competitive_verifier/app.py
competitive_verifier/arg.py
competitive_verifier/check/__init__.py
competitive_verifier/check/main.py
competitive_verifier/config.py
competitive_verifier/documents/__init__.py
competitive_verifier/documents/builder.py
competitive_verifier/documents/config.py
competitive_verifier/documents/front_matter.py
competitive_verifier/documents/main.py
competitive_verifier/documents/render.py
competitive_verifier/documents/render_data.py
competitive_verifier/documents/static_files.py
competitive_verifier/download/__init__.py
competitive_verifier/download/main.py
competitive_verifier/error.py
competitive_verifier/exec.py
competitive_verifier/git.py
competitive_verifier/github.py
competitive_verifier/log.py
competitive_verifier/merge_input/__init__.py
competitive_verifier/merge_input/main.py
competitive_verifier/merge_result/__init__.py
competitive_verifier/merge_result/main.py
competitive_verifier/migrate/__init__.py
competitive_verifier/migrate/main.py
competitive_verifier/migrate/migration.py
competitive_verifier/models/__init__.py
competitive_verifier/models/_scc.py
competitive_verifier/models/file.py
competitive_verifier/models/path.py
competitive_verifier/models/result.py
competitive_verifier/models/result_status.py
competitive_verifier/models/shell.py
competitive_verifier/models/verification.py
competitive_verifier/oj/__init__.py
competitive_verifier/oj/tools/download_command.py
competitive_verifier/oj/tools/func.py
competitive_verifier/oj/tools/output_comparators.py
competitive_verifier/oj/tools/pretty_printers.py
competitive_verifier/oj/tools/test_command.py
competitive_verifier/oj/tools/utils.py
competitive_verifier/oj/verify/__init__.py
competitive_verifier/oj/verify/languages/__init__.py
competitive_verifier/oj/verify/languages/cplusplus.py
competitive_verifier/oj/verify/languages/cplusplus_bundle.py
competitive_verifier/oj/verify/languages/go.py
competitive_verifier/oj/verify/languages/haskell.py
competitive_verifier-3.3.0.dist-info/LICENSE
competitive_verifier-3.3.0.dist-info/METADATA
competitive_verifier-3.3.0.dist-info/WHEEL
competitive_verifier-3.3.0.dist-info/entry_points.txt
competitive_verifier-3.3.0.dist-info/RECORD
