Metadata-Version: 2.1
Name: competitive-verifier
Version: 3.3.0
Summary: Verifier for libraries of competitive programming
Home-page: https://github.com/competitive-verifier/competitive-verifier
License: MIT
Author: kzrnm
Author-email: gengesa@gmail.com
Requires-Python: >=3.9,<4.0
Classifier: License :: OSI Approved :: MIT License
Classifier: Programming Language :: Python :: 3
Classifier: Programming Language :: Python :: 3.9
Classifier: Programming Language :: Python :: 3.10
Classifier: Programming Language :: Python :: 3.11
Classifier: Programming Language :: Python :: 3.12
Classifier: Programming Language :: Python :: 3.13
Requires-Dist: appdirs (>=1.4.4,<2.0.0)
Requires-Dist: beautifulsoup4 (>=4.12.3,<5.0.0)
Requires-Dist: charset-normalizer (>=3.3.2,<4.0.0)
Requires-Dist: colorama (>=0.4.6,<0.5.0)
Requires-Dist: colorlog (>=6.7.0,<7.0.0)
Requires-Dist: importlab (>=0.8,<0.9)
Requires-Dist: pydantic (>=2.0.3,<3.0.0)
Requires-Dist: pyyaml (>=6.0,<7.0)
Requires-Dist: requests (>=2.32.3,<3.0.0)
Requires-Dist: tomli (>=2.0.1,<3.0.0) ; python_version < "3.11"
Project-URL: Repository, https://github.com/competitive-verifier/competitive-verifier
